alphaz_next/__init__.py
alphaz_next/py.typed
alphaz_next/asyncio/__init__.py
alphaz_next/asyncio/async_database.py
alphaz_next/auth/__init__.py
alphaz_next/auth/auth.py
alphaz_next/core/__init__.py
alphaz_next/core/_base.py
alphaz_next/core/_middleware.py
alphaz_next/core/_telemetry.py
alphaz_next/core/application.py
alphaz_next/core/constants.py
alphaz_next/core/exception_handlers.py
alphaz_next/core/exceptions.py
alphaz_next/core/responses/__init__.py
alphaz_next/core/responses/file_response.py
alphaz_next/core/responses/html_response.py
alphaz_next/core/responses/json_response.py
alphaz_next/core/responses/orjson_response.py
alphaz_next/core/responses/plaintext_response.py
alphaz_next/core/responses/redirect_response.py
alphaz_next/core/responses/response.py
alphaz_next/core/responses/streaming_response.py
alphaz_next/core/responses/ujson_response.py
alphaz_next/libs/__init__.py
alphaz_next/libs/file_lib.py
alphaz_next/libs/httpx.py
alphaz_next/models/__init__.py
alphaz_next/models/auth/__init__.py
alphaz_next/models/auth/user.py
alphaz_next/models/config/__init__.py
alphaz_next/models/config/alpha_config.py
alphaz_next/models/config/api_config.py
alphaz_next/models/config/apm_config.py
alphaz_next/models/config/config_settings.py
alphaz_next/models/config/database_config.py
alphaz_next/models/config/directories_config.py
alphaz_next/models/config/logging_config.py
alphaz_next/models/config/openapi_config_schema.py
alphaz_next/models/config/_base/__init__.py
alphaz_next/models/config/_base/internal_config_settings.py
alphaz_next/models/config/_base/utils.py
alphaz_next/tests/__init__.py
alphaz_next/tests/utils/__init__.py
alphaz_next/tests/utils/utils.py
alphaz_next/tests/utils/mocking/__init__.py
alphaz_next/tests/utils/mocking/mock_user.py
alphaz_next/utils/__init__.py
alphaz_next/utils/database.py
alphaz_next/utils/format.py
alphaz_next/utils/logger.py
alphaz_next/utils/logging_filters.py
alphaz_next/utils/loguru.py
alphaz_next-0.7.4.0.dist-info/METADATA
alphaz_next-0.7.4.0.dist-info/WHEEL
alphaz_next-0.7.4.0.dist-info/top_level.txt
alphaz_next-0.7.4.0.dist-info/RECORD
