Metadata-Version: 2.1
Name: alphaz-next
Version: 0.7.4.0
Summary: A project to make a lib to start FastAPI quickly
Home-page: https://github.com/STDef200mm/alphaz-next
Download-URL: https://github.com/STDef200mm/alphaz-next/archive/refs/tags/0.7.4.0.tar.gz
Author: Maxime MARTIN
Author-email: Maxime MARTIN <maxime.martin02@hotmail.fr>
License: MIT
Classifier: Development Status :: 3 - Alpha
Classifier: Intended Audience :: Developers
Classifier: License :: OSI Approved :: MIT License
Classifier: Programming Language :: Python :: 3
Requires-Python: >=3.8
Requires-Dist: httpx
Requires-Dist: python-jose
Requires-Dist: python-multipart
Requires-Dist: fastapi >=0.108.0
Requires-Dist: pydantic-settings
Requires-Dist: pydantic <3.0.0,>=2.5
Requires-Dist: sqlalchemy-utils
Requires-Dist: email-validator
Requires-Dist: deepdiff
Requires-Dist: unidecode
Requires-Dist: pysql-repo ==0.7.4.0
Requires-Dist: loguru
Requires-Dist: opentelemetry-api
Requires-Dist: opentelemetry-exporter-otlp-proto-http
Requires-Dist: opentelemetry-instrumentation-fastapi
Requires-Dist: opentelemetry-instrumentation-sqlalchemy
Requires-Dist: opentelemetry-instrumentation-system-metrics
Requires-Dist: opentelemetry-instrumentation-logging
Requires-Dist: opentelemetry-sdk
Provides-Extra: dependency-injector
Requires-Dist: dependency-injector ; extra == 'dependency-injector'
